[
  {
    "id": "metro_arrozintegralextrafa_mml1tbsn",
    "nombre": "Arroz Integral Extra Faraón 500g",
    "categoria": "arroz",
    "super": "metro",
    "precios": {
      "online": 2.99,
      "regular": null,
      "porUnidad": 5.98
    },
    "presentacion": {
      "valor": 500,
      "unidad": "g",
      "pack": 1
    },
    "descuento": 0,
    "timestamp": "2026-03-10T20:14:19.127Z"
  },
  {
    "id": "metro_arrozsuperiormetro75_mml1tbso",
    "nombre": "Arroz Superior Metro 750g",
    "categoria": "arroz",
    "super": "metro",
    "precios": {
      "online": 3.2,
      "regular": null,
      "porUnidad": 4.27
    },
    "presentacion": {
      "valor": 750,
      "unidad": "g",
      "pack": 1
    },
    "descuento": 0,
    "timestamp": "2026-03-10T20:14:19.127Z"
  },
  {
    "id": "metro_arrozextrametro750g_mml1tbso",
    "nombre": "Arroz Extra Metro 750g",
    "categoria": "arroz",
    "super": "metro",
    "precios": {
      "online": 3.5,
      "regular": null,
      "porUnidad": 4.67
    },
    "presentacion": {
      "valor": 750,
      "unidad": "g",
      "pack": 1
    },
    "descuento": 0,
    "timestamp": "2026-03-10T20:14:19.128Z"
  },
  {
    "id": "metro_arrozsuperiorcuisine_mml1tbso",
    "nombre": "Arroz Superior Cuisine & Co 750g",
    "categoria": "arroz",
    "super": "metro",
    "precios": {
      "online": 3.5,
      "regular": null,
      "porUnidad": 4.67
    },
    "presentacion": {
      "valor": 750,
      "unidad": "g",
      "pack": 1
    },
    "descuento": 0,
    "timestamp": "2026-03-10T20:14:19.128Z"
  },
  {
    "id": "metro_arrozextracuisineco7_mml1tbso",
    "nombre": "Arroz Extra Cuisine & Co 750g",
    "categoria": "arroz",
    "super": "metro",
    "precios": {
      "online": 3.9,
      "regular": null,
      "porUnidad": 5.2
    },
    "presentacion": {
      "valor": 750,
      "unidad": "g",
      "pack": 1
    },
    "descuento": 0,
    "timestamp": "2026-03-10T20:14:19.128Z"
  },
  {
    "id": "metro_arrozsuperioraejofar_mml1tbso",
    "nombre": "Arroz Superior Añejo Faraón Rojo 750g",
    "categoria": "arroz",
    "super": "metro",
    "precios": {
      "online": 3.95,
      "regular": null,
      "porUnidad": 5.27
    },
    "presentacion": {
      "valor": 750,
      "unidad": "g",
      "pack": 1
    },
    "descuento": 0,
    "timestamp": "2026-03-10T20:14:19.128Z"
  },
  {
    "id": "metro_alimentohmedopedigre_mml1tbso",
    "nombre": "Alimento Húmedo Pedigree Pouch Salmón y Arroz",
    "categoria": "arroz",
    "super": "metro",
    "precios": {
      "online": 4.1,
      "regular": null,
      "porUnidad": 4.1
    },
    "presentacion": null,
    "descuento": 0,
    "timestamp": "2026-03-10T20:14:19.128Z"
  },
  {
    "id": "metro_arrozgranreservaextr_mml1tbso",
    "nombre": "Arroz Gran Reserva Extra Valle Norte Bolsa 750 g",
    "categoria": "arroz",
    "super": "metro",
    "precios": {
      "online": 4.2,
      "regular": 4.8,
      "porUnidad": 5.6
    },
    "presentacion": {
      "valor": 750,
      "unidad": "g",
      "pack": 1
    },
    "descuento": 12,
    "timestamp": "2026-03-10T20:14:19.128Z"
  },
  {
    "id": "metro_arrozaejoextracuisin_mml1tbso",
    "nombre": "Arroz Añejo Extra Cuisine & Co 750g",
    "categoria": "arroz",
    "super": "metro",
    "precios": {
      "online": 4.2,
      "regular": null,
      "porUnidad": 5.6
    },
    "presentacion": {
      "valor": 750,
      "unidad": "g",
      "pack": 1
    },
    "descuento": 0,
    "timestamp": "2026-03-10T20:14:19.128Z"
  },
  {
    "id": "metro_arrozsuperiorvalleno_mml1tbso",
    "nombre": "Arroz Superior Valle Norte Primera Cosecha Bolsa 750 g",
    "categoria": "arroz",
    "super": "metro",
    "precios": {
      "online": 4.2,
      "regular": null,
      "porUnidad": 5.6
    },
    "presentacion": {
      "valor": 750,
      "unidad": "g",
      "pack": 1
    },
    "descuento": 0,
    "timestamp": "2026-03-10T20:14:19.128Z"
  },
  {
    "id": "metro_arrozcosteoaejoextra_mml1tbso",
    "nombre": "Arroz Costeño Añejo Extra 750g",
    "categoria": "arroz",
    "super": "metro",
    "precios": {
      "online": 4.3,
      "regular": null,
      "porUnidad": 5.73
    },
    "presentacion": {
      "valor": 750,
      "unidad": "g",
      "pack": 1
    },
    "descuento": 0,
    "timestamp": "2026-03-10T20:14:19.128Z"
  },
  {
    "id": "metro_arrozextrapacasmayo7_mml1tbso",
    "nombre": "Arroz Extra Pacasmayo 750g",
    "categoria": "arroz",
    "super": "metro",
    "precios": {
      "online": 4.3,
      "regular": null,
      "porUnidad": 5.73
    },
    "presentacion": {
      "valor": 750,
      "unidad": "g",
      "pack": 1
    },
    "descuento": 0,
    "timestamp": "2026-03-10T20:14:19.128Z"
  },
  {
    "id": "metro_arrozblancoextraaejo_mml1tbso",
    "nombre": "Arroz Blanco Extra Añejo Faraón Naranja 750g",
    "categoria": "arroz",
    "super": "metro",
    "precios": {
      "online": 4.4,
      "regular": null,
      "porUnidad": 5.87
    },
    "presentacion": {
      "valor": 750,
      "unidad": "g",
      "pack": 1
    },
    "descuento": 0,
    "timestamp": "2026-03-10T20:14:19.128Z"
  },
  {
    "id": "metro_arrozextraaejocampon_mml1tbso",
    "nombre": "Arroz Extra Añejo Campo Norte 750g",
    "categoria": "arroz",
    "super": "metro",
    "precios": {
      "online": 4.4,
      "regular": null,
      "porUnidad": 5.87
    },
    "presentacion": {
      "valor": 750,
      "unidad": "g",
      "pack": 1
    },
    "descuento": 0,
    "timestamp": "2026-03-10T20:14:19.128Z"
  },
  {
    "id": "metro_arrozaejopacasmayo75_mml1tbso",
    "nombre": "Arroz Añejo Pacasmayo 750g",
    "categoria": "arroz",
    "super": "metro",
    "precios": {
      "online": 4.49,
      "regular": null,
      "porUnidad": 5.99
    },
    "presentacion": {
      "valor": 750,
      "unidad": "g",
      "pack": 1
    },
    "descuento": 0,
    "timestamp": "2026-03-10T20:14:19.128Z"
  },
  {
    "id": "metro_arrozextracosteo750g_mml1tbso",
    "nombre": "Arroz Extra Costeño 750g",
    "categoria": "arroz",
    "super": "metro",
    "precios": {
      "online": 4.5,
      "regular": null,
      "porUnidad": 6
    },
    "presentacion": {
      "valor": 750,
      "unidad": "g",
      "pack": 1
    },
    "descuento": 0,
    "timestamp": "2026-03-10T20:14:19.128Z"
  },
  {
    "id": "metro_arrozintegralcuisine_mml1tbso",
    "nombre": "Arroz Integral Cuisine & Co 750g",
    "categoria": "arroz",
    "super": "metro",
    "precios": {
      "online": 4.5,
      "regular": null,
      "porUnidad": 6
    },
    "presentacion": {
      "valor": 750,
      "unidad": "g",
      "pack": 1
    },
    "descuento": 0,
    "timestamp": "2026-03-10T20:14:19.128Z"
  },
  {
    "id": "metro_arrozreservaextracam_mml1tbso",
    "nombre": "Arroz Reserva Extra Campero 1kg",
    "categoria": "arroz",
    "super": "metro",
    "precios": {
      "online": 4.5,
      "regular": 5.8,
      "porUnidad": 4.5
    },
    "presentacion": {
      "valor": 1,
      "unidad": "kg",
      "pack": 1
    },
    "descuento": 22,
    "timestamp": "2026-03-10T20:14:19.128Z"
  },
  {
    "id": "metro_arrozsuperiorcosteo7_mml1tbso",
    "nombre": "Arroz Superior Costeño 750g",
    "categoria": "arroz",
    "super": "metro",
    "precios": {
      "online": 4.5,
      "regular": null,
      "porUnidad": 6
    },
    "presentacion": {
      "valor": 750,
      "unidad": "g",
      "pack": 1
    },
    "descuento": 0,
    "timestamp": "2026-03-10T20:14:19.128Z"
  },
  {
    "id": "metro_arrozsuperiorgrancha_mml1tbso",
    "nombre": "Arroz Superior Gran Chalán 750g",
    "categoria": "arroz",
    "super": "metro",
    "precios": {
      "online": 4.5,
      "regular": null,
      "porUnidad": 6
    },
    "presentacion": {
      "valor": 750,
      "unidad": "g",
      "pack": 1
    },
    "descuento": 0,
    "timestamp": "2026-03-10T20:14:19.128Z"
  },
  {
    "id": "metro_arrozintegralmolinor_mml1tbso",
    "nombre": "Arroz Integral Molino Rojo Bolsa 1 Kg",
    "categoria": "arroz",
    "super": "metro",
    "precios": {
      "online": 4.9,
      "regular": null,
      "porUnidad": 4.9
    },
    "presentacion": {
      "valor": 1,
      "unidad": "kg",
      "pack": 1
    },
    "descuento": 0,
    "timestamp": "2026-03-10T20:14:19.128Z"
  },
  {
    "id": "metro_compotasmileykidsper_mml1tbso",
    "nombre": "Compota Smiley Kids Pera, Zapallito, Espinaca y Arroz 90g",
    "categoria": "arroz",
    "super": "metro",
    "precios": {
      "online": 4.9,
      "regular": 5.9,
      "porUnidad": 54.44
    },
    "presentacion": {
      "valor": 90,
      "unidad": "g",
      "pack": 1
    },
    "descuento": 17,
    "timestamp": "2026-03-10T20:14:19.128Z"
  },
  {
    "id": "metro_arrozextragranchaln7_mml1tbso",
    "nombre": "Arroz Extra Gran Chalán 750g",
    "categoria": "arroz",
    "super": "metro",
    "precios": {
      "online": 4.9,
      "regular": null,
      "porUnidad": 6.53
    },
    "presentacion": {
      "valor": 750,
      "unidad": "g",
      "pack": 1
    },
    "descuento": 0,
    "timestamp": "2026-03-10T20:14:19.128Z"
  },
  {
    "id": "metro_arrozintegralextrabo_mml1tbso",
    "nombre": "Arroz Integral Extra Bolsa 750 g",
    "categoria": "arroz",
    "super": "metro",
    "precios": {
      "online": 5.15,
      "regular": null,
      "porUnidad": 6.87
    },
    "presentacion": {
      "valor": 750,
      "unidad": "g",
      "pack": 1
    },
    "descuento": 0,
    "timestamp": "2026-03-10T20:14:19.128Z"
  },
  {
    "id": "metro_lrrmoldeparaarroznro_mml1tbso",
    "nombre": "LRR Molde para Arroz Nro 1 25 x 30 cm",
    "categoria": "arroz",
    "super": "metro",
    "precios": {
      "online": 5.39,
      "regular": 8.99,
      "porUnidad": 5.39
    },
    "presentacion": null,
    "descuento": 40,
    "timestamp": "2026-03-10T20:14:19.128Z"
  },
  {
    "id": "metro_trocitosensalsaricoc_mml1tbso",
    "nombre": "Trocitos en Salsa Ricocan Adultos Cordero y Arroz 290g",
    "categoria": "arroz",
    "super": "metro",
    "precios": {
      "online": 5.5,
      "regular": 7.9,
      "porUnidad": 18.97
    },
    "presentacion": {
      "valor": 290,
      "unidad": "g",
      "pack": 1
    },
    "descuento": 30,
    "timestamp": "2026-03-10T20:14:19.128Z"
  },
  {
    "id": "metro_arrozparbolizadocost_mml1tbso",
    "nombre": "Arroz Parbolizado Costeño 750g",
    "categoria": "arroz",
    "super": "metro",
    "precios": {
      "online": 5.6,
      "regular": null,
      "porUnidad": 7.47
    },
    "presentacion": {
      "valor": 750,
      "unidad": "g",
      "pack": 1
    },
    "descuento": 0,
    "timestamp": "2026-03-10T20:14:19.128Z"
  },
  {
    "id": "metro_arrozintegralvalleno_mml1tbso",
    "nombre": "Arroz Integral Vallenorte 750g",
    "categoria": "arroz",
    "super": "metro",
    "precios": {
      "online": 5.6,
      "regular": null,
      "porUnidad": 7.47
    },
    "presentacion": {
      "valor": 750,
      "unidad": "g",
      "pack": 1
    },
    "descuento": 0,
    "timestamp": "2026-03-10T20:14:19.128Z"
  },
  {
    "id": "metro_arrozsuperiorpaisana_mml1tbso",
    "nombre": "Arroz Superior Paisana Bolsa 1 kg",
    "categoria": "arroz",
    "super": "metro",
    "precios": {
      "online": 5.7,
      "regular": null,
      "porUnidad": 5.7
    },
    "presentacion": {
      "valor": 1,
      "unidad": "kg",
      "pack": 1
    },
    "descuento": 0,
    "timestamp": "2026-03-10T20:14:19.128Z"
  },
  {
    "id": "metro_arrozintegralcosteo7_mml1tbso",
    "nombre": "Arroz Integral Costeño 750g",
    "categoria": "arroz",
    "super": "metro",
    "precios": {
      "online": 5.8,
      "regular": null,
      "porUnidad": 7.73
    },
    "presentacion": {
      "valor": 750,
      "unidad": "g",
      "pack": 1
    },
    "descuento": 0,
    "timestamp": "2026-03-10T20:14:19.128Z"
  },
  {
    "id": "metro_arrozextrapaisanabol_mml1tbsp",
    "nombre": "Arroz Extra Paisana Bolsa 1 kg",
    "categoria": "arroz",
    "super": "metro",
    "precios": {
      "online": 5.9,
      "regular": null,
      "porUnidad": 5.9
    },
    "presentacion": {
      "valor": 1,
      "unidad": "kg",
      "pack": 1
    },
    "descuento": 0,
    "timestamp": "2026-03-10T20:14:19.128Z"
  },
  {
    "id": "metro_arrozjapnicoparasush_mml1tbsp",
    "nombre": "Arroz Japónico para Sushi Bárcidda 500g",
    "categoria": "arroz",
    "super": "metro",
    "precios": {
      "online": 5.9,
      "regular": null,
      "porUnidad": 11.8
    },
    "presentacion": {
      "valor": 500,
      "unidad": "g",
      "pack": 1
    },
    "descuento": 0,
    "timestamp": "2026-03-10T20:14:19.129Z"
  },
  {
    "id": "metro_arrozintegralpaisana_mml1tbsp",
    "nombre": "Arroz Integral Paisana Bolsa 1 kg",
    "categoria": "arroz",
    "super": "metro",
    "precios": {
      "online": 6.5,
      "regular": null,
      "porUnidad": 6.5
    },
    "presentacion": {
      "valor": 1,
      "unidad": "kg",
      "pack": 1
    },
    "descuento": 0,
    "timestamp": "2026-03-10T20:14:19.129Z"
  },
  {
    "id": "metro_arrozparbolizadopais_mml1tbsp",
    "nombre": "Arroz Parbolizado Paisana Bolsa 1 kg",
    "categoria": "arroz",
    "super": "metro",
    "precios": {
      "online": 7,
      "regular": null,
      "porUnidad": 7
    },
    "presentacion": {
      "valor": 1,
      "unidad": "kg",
      "pack": 1
    },
    "descuento": 0,
    "timestamp": "2026-03-10T20:14:19.129Z"
  },
  {
    "id": "metro_lrrmoldeparaarroznro_mml1tbsp",
    "nombre": "LRR Molde para Arroz Nro 3 35 x 35 cm",
    "categoria": "arroz",
    "super": "metro",
    "precios": {
      "online": 7.19,
      "regular": 11.99,
      "porUnidad": 7.19
    },
    "presentacion": null,
    "descuento": 40,
    "timestamp": "2026-03-10T20:14:19.129Z"
  },
  {
    "id": "metro_arrozblancocuisineco_mml1tbsp",
    "nombre": "Arroz Blanco Cuisine & Co 400g",
    "categoria": "arroz",
    "super": "metro",
    "precios": {
      "online": 7.2,
      "regular": null,
      "porUnidad": 18
    },
    "presentacion": {
      "valor": 400,
      "unidad": "g",
      "pack": 1
    },
    "descuento": 0,
    "timestamp": "2026-03-10T20:14:19.129Z"
  },
  {
    "id": "metro_arrozglaseadotesorod_mml1tbsp",
    "nombre": "Arroz Glaseado Tesoro Del Campo Bolsa 1 Kg",
    "categoria": "arroz",
    "super": "metro",
    "precios": {
      "online": 7.8,
      "regular": null,
      "porUnidad": 7.8
    },
    "presentacion": {
      "valor": 1,
      "unidad": "kg",
      "pack": 1
    },
    "descuento": 0,
    "timestamp": "2026-03-10T20:14:19.129Z"
  },
  {
    "id": "metro_fideosdearrozbrcidda_mml1tbsp",
    "nombre": "Fideos de Arroz Bárcidda 250g",
    "categoria": "arroz",
    "super": "metro",
    "precios": {
      "online": 7.9,
      "regular": null,
      "porUnidad": 31.6
    },
    "presentacion": {
      "valor": 250,
      "unidad": "g",
      "pack": 1
    },
    "descuento": 0,
    "timestamp": "2026-03-10T20:14:19.129Z"
  },
  {
    "id": "metro_harinadearrozcosteo1_mml1tbsp",
    "nombre": "Harina de Arroz Costeño 1 g",
    "categoria": "arroz",
    "super": "metro",
    "precios": {
      "online": 8.9,
      "regular": null,
      "porUnidad": 8900
    },
    "presentacion": {
      "valor": 1,
      "unidad": "g",
      "pack": 1
    },
    "descuento": 0,
    "timestamp": "2026-03-10T20:14:19.129Z"
  },
  {
    "id": "metro_baseparaarrozconpoll_mml1tbsp",
    "nombre": "Base para Arroz con Pollo Provenzal Sobre 58 g",
    "categoria": "arroz",
    "super": "metro",
    "precios": {
      "online": 9.2,
      "regular": null,
      "porUnidad": 158.62
    },
    "presentacion": {
      "valor": 58,
      "unidad": "g",
      "pack": 1
    },
    "descuento": 0,
    "timestamp": "2026-03-10T20:14:19.129Z"
  },
  {
    "id": "metro_fideosdearrozfansive_mml1tbsp",
    "nombre": "Fideos de Arroz Fansi Vermicelli 250g",
    "categoria": "arroz",
    "super": "metro",
    "precios": {
      "online": 9.7,
      "regular": null,
      "porUnidad": 38.8
    },
    "presentacion": {
      "valor": 250,
      "unidad": "g",
      "pack": 1
    },
    "descuento": 0,
    "timestamp": "2026-03-10T20:14:19.129Z"
  },
  {
    "id": "metro_verduraspicadasparaa_mml1tbsp",
    "nombre": "Verduras Picadas para Arroz con Pollo Cuisine & Co 200g",
    "categoria": "arroz",
    "super": "metro",
    "precios": {
      "online": 10.5,
      "regular": null,
      "porUnidad": 52.5
    },
    "presentacion": {
      "valor": 200,
      "unidad": "g",
      "pack": 1
    },
    "descuento": 0,
    "timestamp": "2026-03-10T20:14:19.129Z"
  },
  {
    "id": "metro_arrozchaufacuisineco_mml1tbsp",
    "nombre": "Arroz Chaufa Cuisine & Co 500g",
    "categoria": "arroz",
    "super": "metro",
    "precios": {
      "online": 10.99,
      "regular": null,
      "porUnidad": 21.98
    },
    "presentacion": {
      "valor": 500,
      "unidad": "g",
      "pack": 1
    },
    "descuento": 0,
    "timestamp": "2026-03-10T20:14:19.129Z"
  },
  {
    "id": "metro_arrozaejoextracampon_mml1tbsp",
    "nombre": "Arroz Añejo Extra Campo Norte 2.5kg",
    "categoria": "arroz",
    "super": "metro",
    "precios": {
      "online": 11.5,
      "regular": 13.2,
      "porUnidad": 4.6
    },
    "presentacion": {
      "valor": 2.5,
      "unidad": "kg",
      "pack": 1
    },
    "descuento": 13,
    "timestamp": "2026-03-10T20:14:19.129Z"
  },
  {
    "id": "metro_arrozarboriocosteo75_mml1tbsp",
    "nombre": "Arroz Arborio Costeño 750g",
    "categoria": "arroz",
    "super": "metro",
    "precios": {
      "online": 11.9,
      "regular": null,
      "porUnidad": 15.87
    },
    "presentacion": {
      "valor": 750,
      "unidad": "g",
      "pack": 1
    },
    "descuento": 0,
    "timestamp": "2026-03-10T20:14:19.129Z"
  }
]