[
  {
    "id": "plazavea_pandemoldeblancoxlbi_mmgpp96p",
    "nombre": "Pan de Molde Blanco XL BIMBO Extra Grande Bols...",
    "categoria": "pan",
    "super": "plazavea",
    "precios": {
      "online": 9.9,
      "regular": 12.5,
      "porUnidad": 9.9
    },
    "presentacion": null,
    "descuento": 21,
    "timestamp": "2026-03-07T19:24:09.024Z"
  },
  {
    "id": "plazavea_pandemoldeintegralxl_mmgpp96p",
    "nombre": "Pan de Molde Integral XL BIMBO Extra Grande Bo...",
    "categoria": "pan",
    "super": "plazavea",
    "precios": {
      "online": 9.9,
      "regular": 12.5,
      "porUnidad": 9.9
    },
    "presentacion": null,
    "descuento": 21,
    "timestamp": "2026-03-07T19:24:09.024Z"
  },
  {
    "id": "plazavea_panartesanoblancobim_mmgpp96p",
    "nombre": "Pan Artesano Blanco BIMBO Bolsa 560g",
    "categoria": "pan",
    "super": "plazavea",
    "precios": {
      "online": 12.2,
      "regular": null,
      "porUnidad": 21.79
    },
    "presentacion": {
      "valor": 560,
      "unidad": "g",
      "pack": 1
    },
    "descuento": 0,
    "timestamp": "2026-03-07T19:24:09.024Z"
  },
  {
    "id": "plazavea_pandemoldeintegralbi_mmgpp96p",
    "nombre": "Pan de Molde Integral BIMBO Vital Multicereal ...",
    "categoria": "pan",
    "super": "plazavea",
    "precios": {
      "online": 8.9,
      "regular": 10.5,
      "porUnidad": 8.9
    },
    "presentacion": null,
    "descuento": 15,
    "timestamp": "2026-03-07T19:24:09.024Z"
  },
  {
    "id": "plazavea_pandemoldeintegralbi_mmgpp96p",
    "nombre": "Pan de Molde Integral BIMBO Vital Multicereal ...",
    "categoria": "pan",
    "super": "plazavea",
    "precios": {
      "online": 13.2,
      "regular": 14.8,
      "porUnidad": 13.2
    },
    "presentacion": null,
    "descuento": 11,
    "timestamp": "2026-03-07T19:24:09.024Z"
  },
  {
    "id": "plazavea_pandemoldeblancodonm_mmgpp96p",
    "nombre": "Pan de Molde Blanco DON MAMINO sin Corteza Bol...",
    "categoria": "pan",
    "super": "plazavea",
    "precios": {
      "online": 13.49,
      "regular": null,
      "porUnidad": 13.49
    },
    "presentacion": null,
    "descuento": 0,
    "timestamp": "2026-03-07T19:24:09.024Z"
  },
  {
    "id": "plazavea_panblancobimbosinbor_mmgpp96p",
    "nombre": "Pan Blanco BIMBO sin Bordes Bolsa 590g",
    "categoria": "pan",
    "super": "plazavea",
    "precios": {
      "online": 10.9,
      "regular": 13.5,
      "porUnidad": 18.47
    },
    "presentacion": {
      "valor": 590,
      "unidad": "g",
      "pack": 1
    },
    "descuento": 19,
    "timestamp": "2026-03-07T19:24:09.024Z"
  },
  {
    "id": "plazavea_pandemoldebimbovital_mmgpp96p",
    "nombre": "Pan de Molde BIMBO Vital Semillas Bolsa 360g",
    "categoria": "pan",
    "super": "plazavea",
    "precios": {
      "online": 8.9,
      "regular": 10.5,
      "porUnidad": 24.72
    },
    "presentacion": {
      "valor": 360,
      "unidad": "g",
      "pack": 1
    },
    "descuento": 15,
    "timestamp": "2026-03-07T19:24:09.024Z"
  },
  {
    "id": "plazavea_pandemoldeuninmultis_mmgpp96p",
    "nombre": "Pan de Molde UNIÓN Multisemillas y Avena Bolsa...",
    "categoria": "pan",
    "super": "plazavea",
    "precios": {
      "online": 10.8,
      "regular": 11.4,
      "porUnidad": 10.8
    },
    "presentacion": null,
    "descuento": 5,
    "timestamp": "2026-03-07T19:24:09.024Z"
  },
  {
    "id": "plazavea_pandemoldeuningranos_mmgpp96p",
    "nombre": "Pan de Molde UNIÓN Granos Integrales Bolsa 540...",
    "categoria": "pan",
    "super": "plazavea",
    "precios": {
      "online": 10.8,
      "regular": 11.4,
      "porUnidad": 10.8
    },
    "presentacion": null,
    "descuento": 5,
    "timestamp": "2026-03-07T19:24:09.024Z"
  },
  {
    "id": "plazavea_pandemoldeblancobimb_mmgpp96p",
    "nombre": "Pan de Molde Blanco BIMBO Vital de Semillas Bo...",
    "categoria": "pan",
    "super": "plazavea",
    "precios": {
      "online": 12.9,
      "regular": 14.8,
      "porUnidad": 12.9
    },
    "presentacion": null,
    "descuento": 13,
    "timestamp": "2026-03-07T19:24:09.024Z"
  },
  {
    "id": "plazavea_pandemoldebimboblanc_mmgpp96p",
    "nombre": "Pan de Molde BIMBO Blanco Familiar Bolsa 590g",
    "categoria": "pan",
    "super": "plazavea",
    "precios": {
      "online": 9.5,
      "regular": 9.9,
      "porUnidad": 16.1
    },
    "presentacion": {
      "valor": 590,
      "unidad": "g",
      "pack": 1
    },
    "descuento": 4,
    "timestamp": "2026-03-07T19:24:09.024Z"
  },
  {
    "id": "plazavea_pandemoldebimbointeg_mmgpp96p",
    "nombre": "Pan de Molde BIMBO Integral Cero Cero Bolsa 65...",
    "categoria": "pan",
    "super": "plazavea",
    "precios": {
      "online": 10.8,
      "regular": 12,
      "porUnidad": 10.8
    },
    "presentacion": null,
    "descuento": 10,
    "timestamp": "2026-03-07T19:24:09.024Z"
  },
  {
    "id": "plazavea_pandemoldeintegralmu_mmgpp96p",
    "nombre": "Pan de Molde Integral Multicereal LA FLORENCIA...",
    "categoria": "pan",
    "super": "plazavea",
    "precios": {
      "online": 12.9,
      "regular": null,
      "porUnidad": 12.9
    },
    "presentacion": null,
    "descuento": 0,
    "timestamp": "2026-03-07T19:24:09.024Z"
  },
  {
    "id": "plazavea_pandemoldeuninmultis_mmgpp96p",
    "nombre": "Pan de Molde UNIÓN Multisemillas y Chips de Mi...",
    "categoria": "pan",
    "super": "plazavea",
    "precios": {
      "online": 10.8,
      "regular": 12.9,
      "porUnidad": 10.8
    },
    "presentacion": null,
    "descuento": 16,
    "timestamp": "2026-03-07T19:24:09.024Z"
  },
  {
    "id": "plazavea_pandemoldeintegralbe_mmgpp96p",
    "nombre": "Pan de Molde Integral BELL'S Mediano Bolsa 500...",
    "categoria": "pan",
    "super": "plazavea",
    "precios": {
      "online": 7.5,
      "regular": null,
      "porUnidad": 7.5
    },
    "presentacion": null,
    "descuento": 0,
    "timestamp": "2026-03-07T19:24:09.024Z"
  },
  {
    "id": "plazavea_pandemoldeblancobell_mmgpp96p",
    "nombre": "Pan de Molde Blanco BELL'S Mediano Bolsa 500g",
    "categoria": "pan",
    "super": "plazavea",
    "precios": {
      "online": 7.5,
      "regular": null,
      "porUnidad": 15
    },
    "presentacion": {
      "valor": 500,
      "unidad": "g",
      "pack": 1
    },
    "descuento": 0,
    "timestamp": "2026-03-07T19:24:09.024Z"
  },
  {
    "id": "plazavea_pandemoldeintegralun_mmgpp96p",
    "nombre": "Pan de Molde Integral UNIÓN Mediano Bolsa 360g",
    "categoria": "pan",
    "super": "plazavea",
    "precios": {
      "online": 8.4,
      "regular": null,
      "porUnidad": 23.33
    },
    "presentacion": {
      "valor": 360,
      "unidad": "g",
      "pack": 1
    },
    "descuento": 0,
    "timestamp": "2026-03-07T19:24:09.024Z"
  },
  {
    "id": "plazavea_panintegralbimbosinb_mmgpp96p",
    "nombre": "Pan Integral BIMBO sin Bordes Bolsa 160g",
    "categoria": "pan",
    "super": "plazavea",
    "precios": {
      "online": 10.9,
      "regular": 13.5,
      "porUnidad": 68.13
    },
    "presentacion": {
      "valor": 160,
      "unidad": "g",
      "pack": 1
    },
    "descuento": 19,
    "timestamp": "2026-03-07T19:24:09.024Z"
  },
  {
    "id": "plazavea_pandemoldebimbointeg_mmgpp96p",
    "nombre": "Pan de Molde BIMBO Integral Familiar Bolsa 620...",
    "categoria": "pan",
    "super": "plazavea",
    "precios": {
      "online": 9.9,
      "regular": null,
      "porUnidad": 9.9
    },
    "presentacion": null,
    "descuento": 0,
    "timestamp": "2026-03-07T19:24:09.024Z"
  },
  {
    "id": "plazavea_pansemihogazaintegra_mmgpp96p",
    "nombre": "Pan Semi Hogaza Integral ORNO Bolsa 400g",
    "categoria": "pan",
    "super": "plazavea",
    "precios": {
      "online": 10.9,
      "regular": null,
      "porUnidad": 27.25
    },
    "presentacion": {
      "valor": 400,
      "unidad": "g",
      "pack": 1
    },
    "descuento": 0,
    "timestamp": "2026-03-07T19:24:09.024Z"
  },
  {
    "id": "plazavea_panintegralbauduccob_mmgpp96p",
    "nombre": "Pan Integral BAUDUCCO Bolsa 390g",
    "categoria": "pan",
    "super": "plazavea",
    "precios": {
      "online": 8.2,
      "regular": 9.5,
      "porUnidad": 21.03
    },
    "presentacion": {
      "valor": 390,
      "unidad": "g",
      "pack": 1
    },
    "descuento": 14,
    "timestamp": "2026-03-07T19:24:09.024Z"
  },
  {
    "id": "plazavea_panblancopycbolsa480_mmgpp96p",
    "nombre": "Pan Blanco PYC Bolsa 480g",
    "categoria": "pan",
    "super": "plazavea",
    "precios": {
      "online": 7.9,
      "regular": null,
      "porUnidad": 16.46
    },
    "presentacion": {
      "valor": 480,
      "unidad": "g",
      "pack": 1
    },
    "descuento": 0,
    "timestamp": "2026-03-07T19:24:09.024Z"
  },
  {
    "id": "plazavea_panvitalmixdequinuas_mmgpp96p",
    "nombre": "Pan VITAL Mix de Quinuas Bolsa 600g",
    "categoria": "pan",
    "super": "plazavea",
    "precios": {
      "online": 12.9,
      "regular": 14.8,
      "porUnidad": 21.5
    },
    "presentacion": {
      "valor": 600,
      "unidad": "g",
      "pack": 1
    },
    "descuento": 13,
    "timestamp": "2026-03-07T19:24:09.025Z"
  },
  {
    "id": "plazavea_pandemoldeintegral6s_mmgpp96p",
    "nombre": "Pan de Molde Integral 6 Semillas LA FLORENCIA ...",
    "categoria": "pan",
    "super": "plazavea",
    "precios": {
      "online": 12.9,
      "regular": null,
      "porUnidad": 12.9
    },
    "presentacion": null,
    "descuento": 0,
    "timestamp": "2026-03-07T19:24:09.025Z"
  },
  {
    "id": "plazavea_pandemoldeintegralpy_mmgpp96p",
    "nombre": "Pan de Molde Integral PYC Mediano Bolsa 500g",
    "categoria": "pan",
    "super": "plazavea",
    "precios": {
      "online": 7.9,
      "regular": null,
      "porUnidad": 15.8
    },
    "presentacion": {
      "valor": 500,
      "unidad": "g",
      "pack": 1
    },
    "descuento": 0,
    "timestamp": "2026-03-07T19:24:09.025Z"
  },
  {
    "id": "plazavea_pandemoldeblancobell_mmgpp96s",
    "nombre": "Pan de Molde Blanco BELL’S Tipo Fuente Corte V...",
    "categoria": "pan",
    "super": "plazavea",
    "precios": {
      "online": 11.2,
      "regular": null,
      "porUnidad": 11.2
    },
    "presentacion": null,
    "descuento": 0,
    "timestamp": "2026-03-07T19:24:09.025Z"
  },
  {
    "id": "plazavea_pandemoldelaflorenci_mmgpp96s",
    "nombre": "Pan de Molde LA FLORENCIA Integral Bolsa 350g",
    "categoria": "pan",
    "super": "plazavea",
    "precios": {
      "online": 6.5,
      "regular": null,
      "porUnidad": 18.57
    },
    "presentacion": {
      "valor": 350,
      "unidad": "g",
      "pack": 1
    },
    "descuento": 0,
    "timestamp": "2026-03-07T19:24:09.025Z"
  },
  {
    "id": "plazavea_pandemoldeintegralun_mmgpp96s",
    "nombre": "Pan de Molde Integral UNIÓN Bolsa 495g",
    "categoria": "pan",
    "super": "plazavea",
    "precios": {
      "online": 12.7,
      "regular": null,
      "porUnidad": 25.66
    },
    "presentacion": {
      "valor": 495,
      "unidad": "g",
      "pack": 1
    },
    "descuento": 0,
    "timestamp": "2026-03-07T19:24:09.025Z"
  },
  {
    "id": "plazavea_pandemoldeuninfibram_mmgpp96s",
    "nombre": "Pan de Molde UNIÓN Fibra Multicereal Bolsa 540...",
    "categoria": "pan",
    "super": "plazavea",
    "precios": {
      "online": 10.8,
      "regular": 12.7,
      "porUnidad": 10.8
    },
    "presentacion": null,
    "descuento": 15,
    "timestamp": "2026-03-07T19:24:09.025Z"
  },
  {
    "id": "plazavea_pansemihogazacampesi_mmgpp96s",
    "nombre": "Pan Semi Hogaza Campesino ORNO Bolsa 400g",
    "categoria": "pan",
    "super": "plazavea",
    "precios": {
      "online": 10.9,
      "regular": null,
      "porUnidad": 27.25
    },
    "presentacion": {
      "valor": 400,
      "unidad": "g",
      "pack": 1
    },
    "descuento": 0,
    "timestamp": "2026-03-07T19:24:09.025Z"
  },
  {
    "id": "plazavea_panblancobauduccobol_mmgpp96s",
    "nombre": "Pan Blanco BAUDUCCO Bolsa 390g",
    "categoria": "pan",
    "super": "plazavea",
    "precios": {
      "online": 8.2,
      "regular": 9.5,
      "porUnidad": 21.03
    },
    "presentacion": {
      "valor": 390,
      "unidad": "g",
      "pack": 1
    },
    "descuento": 14,
    "timestamp": "2026-03-07T19:24:09.025Z"
  },
  {
    "id": "plazavea_panamericanosandwich_mmgpp96s",
    "nombre": "Pan Americano Sandwich UNIÓN Bolsa 540g",
    "categoria": "pan",
    "super": "plazavea",
    "precios": {
      "online": 7.1,
      "regular": 9.5,
      "porUnidad": 13.15
    },
    "presentacion": {
      "valor": 540,
      "unidad": "g",
      "pack": 1
    },
    "descuento": 25,
    "timestamp": "2026-03-07T19:24:09.025Z"
  },
  {
    "id": "plazavea_pandemoldelaflorenci_mmgpp96s",
    "nombre": "Pan de Molde LA FLORENCIA Bolsa 350g",
    "categoria": "pan",
    "super": "plazavea",
    "precios": {
      "online": 6.5,
      "regular": null,
      "porUnidad": 18.57
    },
    "presentacion": {
      "valor": 350,
      "unidad": "g",
      "pack": 1
    },
    "descuento": 0,
    "timestamp": "2026-03-07T19:24:09.025Z"
  },
  {
    "id": "plazavea_pandemoldeblancodonm_mmgpp96s",
    "nombre": "Pan de Molde Blanco DON MAMINO Pullman Corte H...",
    "categoria": "pan",
    "super": "plazavea",
    "precios": {
      "online": 13.5,
      "regular": null,
      "porUnidad": 13.5
    },
    "presentacion": null,
    "descuento": 0,
    "timestamp": "2026-03-07T19:24:09.025Z"
  },
  {
    "id": "plazavea_pandemoldeconavenaor_mmgpp96s",
    "nombre": "Pan de Molde con Avena ORNO Bolsa 600g",
    "categoria": "pan",
    "super": "plazavea",
    "precios": {
      "online": 13.9,
      "regular": null,
      "porUnidad": 23.17
    },
    "presentacion": {
      "valor": 600,
      "unidad": "g",
      "pack": 1
    },
    "descuento": 0,
    "timestamp": "2026-03-07T19:24:09.025Z"
  },
  {
    "id": "plazavea_pandemoldeintegralmo_mmgpp96s",
    "nombre": "Pan de Molde Integral MOLINOS DEL MUNDO Sin Gl...",
    "categoria": "pan",
    "super": "plazavea",
    "precios": {
      "online": 17.2,
      "regular": 21,
      "porUnidad": 17.2
    },
    "presentacion": null,
    "descuento": 18,
    "timestamp": "2026-03-07T19:24:09.025Z"
  },
  {
    "id": "plazavea_pandemoldemolinosdel_mmgpp96s",
    "nombre": "Pan de Molde MOLINOS DEL MUNDO Sin Gluten y Si...",
    "categoria": "pan",
    "super": "plazavea",
    "precios": {
      "online": 17.2,
      "regular": null,
      "porUnidad": 17.2
    },
    "presentacion": null,
    "descuento": 0,
    "timestamp": "2026-03-07T19:24:09.025Z"
  },
  {
    "id": "plazavea_panfuenteuninbolsa78_mmgpp96s",
    "nombre": "Pan Fuente UNIÓN Bolsa 780g",
    "categoria": "pan",
    "super": "plazavea",
    "precios": {
      "online": 11.5,
      "regular": 12.7,
      "porUnidad": 14.74
    },
    "presentacion": {
      "valor": 780,
      "unidad": "g",
      "pack": 1
    },
    "descuento": 9,
    "timestamp": "2026-03-07T19:24:09.025Z"
  }
]