[
  {
    "id": "plazavea_salmarinaemsalcocina_mmgput24",
    "nombre": "Sal Marina EMSAL Cocina Bolsa 1Kg",
    "categoria": "condimentos",
    "super": "plazavea",
    "precios": {
      "online": 2.6,
      "regular": null,
      "porUnidad": 2.6
    },
    "presentacion": {
      "valor": 1,
      "unidad": "kg",
      "pack": 1
    },
    "descuento": 0,
    "timestamp": "2026-03-07T19:28:28.059Z"
  },
  {
    "id": "plazavea_pimientabellsnegramo_mmgput24",
    "nombre": "Pimienta BELL'S Negra molida Sobre 18Gr",
    "categoria": "condimentos",
    "super": "plazavea",
    "precios": {
      "online": 1.9,
      "regular": null,
      "porUnidad": 105.56
    },
    "presentacion": {
      "valor": 18,
      "unidad": "g",
      "pack": 1
    },
    "descuento": 0,
    "timestamp": "2026-03-07T19:28:28.060Z"
  },
  {
    "id": "plazavea_saldemarasfinaonzado_mmgput24",
    "nombre": "Sal de Maras Fina ONZA Doypack 500g",
    "categoria": "condimentos",
    "super": "plazavea",
    "precios": {
      "online": 9.4,
      "regular": null,
      "porUnidad": 18.8
    },
    "presentacion": {
      "valor": 500,
      "unidad": "g",
      "pack": 1
    },
    "descuento": 0,
    "timestamp": "2026-03-07T19:28:28.060Z"
  },
  {
    "id": "plazavea_pimientamolidasibari_mmgput24",
    "nombre": "Pimienta Molida SIBARITA Sobre 21.6g Bolsa 6un",
    "categoria": "condimentos",
    "super": "plazavea",
    "precios": {
      "online": 4.1,
      "regular": null,
      "porUnidad": 189.81
    },
    "presentacion": {
      "valor": 21.6,
      "unidad": "g",
      "pack": 1
    },
    "descuento": 0,
    "timestamp": "2026-03-07T19:28:28.060Z"
  },
  {
    "id": "plazavea_saldemesabellsbolsa1_mmgput24",
    "nombre": "Sal de Mesa BELL'S Bolsa 1 Kg",
    "categoria": "condimentos",
    "super": "plazavea",
    "precios": {
      "online": 2.1,
      "regular": null,
      "porUnidad": 2.1
    },
    "presentacion": {
      "valor": 1,
      "unidad": "kg",
      "pack": 1
    },
    "descuento": 0,
    "timestamp": "2026-03-07T19:28:28.060Z"
  },
  {
    "id": "plazavea_saldecocinabellsbols_mmgput24",
    "nombre": "Sal de Cocina BELL'S Bolsa 1Kg",
    "categoria": "condimentos",
    "super": "plazavea",
    "precios": {
      "online": 2.1,
      "regular": null,
      "porUnidad": 2.1
    },
    "presentacion": {
      "valor": 1,
      "unidad": "kg",
      "pack": 1
    },
    "descuento": 0,
    "timestamp": "2026-03-07T19:28:28.060Z"
  },
  {
    "id": "plazavea_pimientabadianegramo_mmgput24",
    "nombre": "Pimienta BADIA Negra molida Frasco 56.7Gr",
    "categoria": "condimentos",
    "super": "plazavea",
    "precios": {
      "online": 13.1,
      "regular": 13.9,
      "porUnidad": 231.04
    },
    "presentacion": {
      "valor": 56.7,
      "unidad": "g",
      "pack": 1
    },
    "descuento": 6,
    "timestamp": "2026-03-07T19:28:28.060Z"
  },
  {
    "id": "plazavea_pimientakarionegramo_mmgput24",
    "nombre": "Pimienta KARIÑO Negra molida Frasco 40Gr",
    "categoria": "condimentos",
    "super": "plazavea",
    "precios": {
      "online": 7.7,
      "regular": null,
      "porUnidad": 192.5
    },
    "presentacion": {
      "valor": 40,
      "unidad": "g",
      "pack": 1
    },
    "descuento": 0,
    "timestamp": "2026-03-07T19:28:28.060Z"
  },
  {
    "id": "plazavea_saldemarasfinabellsd_mmgput24",
    "nombre": "Sal de Maras Fina BELL'S Doypack 500g",
    "categoria": "condimentos",
    "super": "plazavea",
    "precios": {
      "online": 8.29,
      "regular": null,
      "porUnidad": 16.58
    },
    "presentacion": {
      "valor": 500,
      "unidad": "g",
      "pack": 1
    },
    "descuento": 0,
    "timestamp": "2026-03-07T19:28:28.060Z"
  },
  {
    "id": "plazavea_pimientabellsnegraen_mmgput24",
    "nombre": "Pimienta BELL'S Negra entera Sobre 15Gr",
    "categoria": "condimentos",
    "super": "plazavea",
    "precios": {
      "online": 1.9,
      "regular": null,
      "porUnidad": 126.67
    },
    "presentacion": {
      "valor": 15,
      "unidad": "g",
      "pack": 1
    },
    "descuento": 0,
    "timestamp": "2026-03-07T19:28:28.060Z"
  },
  {
    "id": "plazavea_pimientasibaritasobr_mmgput24",
    "nombre": "Pimienta SIBARITA Sobre 10g",
    "categoria": "condimentos",
    "super": "plazavea",
    "precios": {
      "online": 1.39,
      "regular": null,
      "porUnidad": 139
    },
    "presentacion": {
      "valor": 10,
      "unidad": "g",
      "pack": 1
    },
    "descuento": 0,
    "timestamp": "2026-03-07T19:28:28.060Z"
  },
  {
    "id": "plazavea_salrosadademarasperu_mmgput24",
    "nombre": "Sal Rosada de Maras PERUVIAN Fina Bolsa 500g",
    "categoria": "condimentos",
    "super": "plazavea",
    "precios": {
      "online": 8.9,
      "regular": null,
      "porUnidad": 17.8
    },
    "presentacion": {
      "valor": 500,
      "unidad": "g",
      "pack": 1
    },
    "descuento": 0,
    "timestamp": "2026-03-07T19:28:28.060Z"
  },
  {
    "id": "plazavea_condimentosibaritaaj_mmgput24",
    "nombre": "Condimento SIBARITA Ají especial Paquete 3Un S...",
    "categoria": "condimentos",
    "super": "plazavea",
    "precios": {
      "online": 3.6,
      "regular": null,
      "porUnidad": 1.2
    },
    "presentacion": {
      "valor": 3,
      "unidad": "u",
      "pack": 1
    },
    "descuento": 0,
    "timestamp": "2026-03-07T19:28:28.060Z"
  },
  {
    "id": "plazavea_saldemarasgruesaonza_mmgput24",
    "nombre": "Sal de Maras Gruesa ONZA Doypack 500g",
    "categoria": "condimentos",
    "super": "plazavea",
    "precios": {
      "online": 9.4,
      "regular": null,
      "porUnidad": 18.8
    },
    "presentacion": {
      "valor": 500,
      "unidad": "g",
      "pack": 1
    },
    "descuento": 0,
    "timestamp": "2026-03-07T19:28:28.060Z"
  },
  {
    "id": "plazavea_condimentosibaritatu_mmgput24",
    "nombre": "Condimento SIBARITA Tuco Sobre 32.4Gr",
    "categoria": "condimentos",
    "super": "plazavea",
    "precios": {
      "online": 1.3,
      "regular": null,
      "porUnidad": 40.12
    },
    "presentacion": {
      "valor": 32.4,
      "unidad": "g",
      "pack": 1
    },
    "descuento": 0,
    "timestamp": "2026-03-07T19:28:28.060Z"
  },
  {
    "id": "plazavea_salfinademesaemsalfr_mmgput24",
    "nombre": "Sal Fina de Mesa EMSAL Frasco 500g",
    "categoria": "condimentos",
    "super": "plazavea",
    "precios": {
      "online": 6.1,
      "regular": 7.2,
      "porUnidad": 12.2
    },
    "presentacion": {
      "valor": 500,
      "unidad": "g",
      "pack": 1
    },
    "descuento": 15,
    "timestamp": "2026-03-07T19:28:28.060Z"
  },
  {
    "id": "plazavea_pimientanegrabadiaen_mmgput24",
    "nombre": "Pimienta Negra BADIA en Polvo Frasco 198.4g",
    "categoria": "condimentos",
    "super": "plazavea",
    "precios": {
      "online": 34.5,
      "regular": null,
      "porUnidad": 173.89
    },
    "presentacion": {
      "valor": 198.4,
      "unidad": "g",
      "pack": 1
    },
    "descuento": 0,
    "timestamp": "2026-03-07T19:28:28.060Z"
  },
  {
    "id": "plazavea_saldemarasgruesabell_mmgput24",
    "nombre": "Sal de Maras Gruesa BELL'S Doypack 500g",
    "categoria": "condimentos",
    "super": "plazavea",
    "precios": {
      "online": 8.29,
      "regular": null,
      "porUnidad": 16.58
    },
    "presentacion": {
      "valor": 500,
      "unidad": "g",
      "pack": 1
    },
    "descuento": 0,
    "timestamp": "2026-03-07T19:28:28.060Z"
  },
  {
    "id": "plazavea_salmarinademesaemsal_mmgput24",
    "nombre": "Sal Marina de Mesa EMSAL Ecológica Doypack 500...",
    "categoria": "condimentos",
    "super": "plazavea",
    "precios": {
      "online": 4.99,
      "regular": 5.5,
      "porUnidad": 4.99
    },
    "presentacion": null,
    "descuento": 9,
    "timestamp": "2026-03-07T19:28:28.060Z"
  },
  {
    "id": "plazavea_salrosadademarasperu_mmgput24",
    "nombre": "Sal Rosada de Maras PERUVIAN Gruesa Bolsa 500g",
    "categoria": "condimentos",
    "super": "plazavea",
    "precios": {
      "online": 8.9,
      "regular": null,
      "porUnidad": 17.8
    },
    "presentacion": {
      "valor": 500,
      "unidad": "g",
      "pack": 1
    },
    "descuento": 0,
    "timestamp": "2026-03-07T19:28:28.060Z"
  },
  {
    "id": "plazavea_salparrilleraemsalfr_mmgput24",
    "nombre": "Sal Parrillera EMSAL Frasco 500g",
    "categoria": "condimentos",
    "super": "plazavea",
    "precios": {
      "online": 8.8,
      "regular": 9.7,
      "porUnidad": 17.6
    },
    "presentacion": {
      "valor": 500,
      "unidad": "g",
      "pack": 1
    },
    "descuento": 9,
    "timestamp": "2026-03-07T19:28:28.060Z"
  },
  {
    "id": "plazavea_anticidosaldeandrews_mmgput24",
    "nombre": "Antiácido SAL DE ANDREWS Polvo Efervecente Caj...",
    "categoria": "condimentos",
    "super": "plazavea",
    "precios": {
      "online": 10.8,
      "regular": null,
      "porUnidad": 10.8
    },
    "presentacion": null,
    "descuento": 0,
    "timestamp": "2026-03-07T19:28:28.060Z"
  },
  {
    "id": "plazavea_saldemesalobosfinapo_mmgput24",
    "nombre": "Sal de Mesa LOBOS Fina Pote 125g",
    "categoria": "condimentos",
    "super": "plazavea",
    "precios": {
      "online": 2.6,
      "regular": null,
      "porUnidad": 20.8
    },
    "presentacion": {
      "valor": 125,
      "unidad": "g",
      "pack": 1
    },
    "descuento": 0,
    "timestamp": "2026-03-07T19:28:28.060Z"
  },
  {
    "id": "plazavea_pimienta4estacionesn_mmgput24",
    "nombre": "Pimienta 4 ESTACIONES Negra molida Sobre 60Gr",
    "categoria": "condimentos",
    "super": "plazavea",
    "precios": {
      "online": 7.5,
      "regular": null,
      "porUnidad": 125
    },
    "presentacion": {
      "valor": 60,
      "unidad": "g",
      "pack": 1
    },
    "descuento": 0,
    "timestamp": "2026-03-07T19:28:28.060Z"
  },
  {
    "id": "plazavea_sallobosparillerafra_mmgput24",
    "nombre": "Sal LOBOS Parillera Frasco 750Gr",
    "categoria": "condimentos",
    "super": "plazavea",
    "precios": {
      "online": 7.7,
      "regular": null,
      "porUnidad": 10.27
    },
    "presentacion": {
      "valor": 750,
      "unidad": "g",
      "pack": 1
    },
    "descuento": 0,
    "timestamp": "2026-03-07T19:28:28.060Z"
  },
  {
    "id": "plazavea_salfinademesaemsalfr_mmgput24",
    "nombre": "Sal Fina de Mesa EMSAL Frasco 125g",
    "categoria": "condimentos",
    "super": "plazavea",
    "precios": {
      "online": 4.9,
      "regular": 5.4,
      "porUnidad": 39.2
    },
    "presentacion": {
      "valor": 125,
      "unidad": "g",
      "pack": 1
    },
    "descuento": 9,
    "timestamp": "2026-03-07T19:28:28.060Z"
  },
  {
    "id": "plazavea_pimientatoanegramoli_mmgput24",
    "nombre": "Pimienta TOÑA Negra molida Sobre 18Gr",
    "categoria": "condimentos",
    "super": "plazavea",
    "precios": {
      "online": 3.9,
      "regular": null,
      "porUnidad": 216.67
    },
    "presentacion": {
      "valor": 18,
      "unidad": "g",
      "pack": 1
    },
    "descuento": 0,
    "timestamp": "2026-03-07T19:28:28.060Z"
  },
  {
    "id": "plazavea_saldemarasgruesabell_mmgput24",
    "nombre": "Sal de Maras Gruesa BELL'S Frasco 100g",
    "categoria": "condimentos",
    "super": "plazavea",
    "precios": {
      "online": 12.9,
      "regular": null,
      "porUnidad": 129
    },
    "presentacion": {
      "valor": 100,
      "unidad": "g",
      "pack": 1
    },
    "descuento": 0,
    "timestamp": "2026-03-07T19:28:28.060Z"
  },
  {
    "id": "plazavea_salparrillerabellsfr_mmgput24",
    "nombre": "Sal Parrillera BELL'S Frasco 500g",
    "categoria": "condimentos",
    "super": "plazavea",
    "precios": {
      "online": 7.7,
      "regular": null,
      "porUnidad": 15.4
    },
    "presentacion": {
      "valor": 500,
      "unidad": "g",
      "pack": 1
    },
    "descuento": 0,
    "timestamp": "2026-03-07T19:28:28.060Z"
  },
  {
    "id": "plazavea_saldemarasonzahierba_mmgput24",
    "nombre": "Sal de Maras ONZA Hierbas Mediterráneas Doypac...",
    "categoria": "condimentos",
    "super": "plazavea",
    "precios": {
      "online": 8.7,
      "regular": null,
      "porUnidad": 8.7
    },
    "presentacion": null,
    "descuento": 0,
    "timestamp": "2026-03-07T19:28:28.060Z"
  }
]